libconf.py
libconf-2.0.0.dist-info/METADATA
libconf-2.0.0.dist-info/RECORD
libconf-2.0.0.dist-info/WHEEL
libconf-2.0.0.dist-info/top_level.txt
