Metadata-Version: 2.1
Name: libconf
Version: 2.0.0
Summary: A pure-Python libconfig reader/writer with permissive license
Home-page: https://github.com/Grk0/python-libconf
Author: Christian Aichinger
Author-email: Greek0@gmx.net
License: MIT
Download-URL: https://github.com/Grk0/python-libconf/tarball/2.0.0
Keywords: libconfig configuration parser library
Platform: UNKNOWN
Classifier: Development Status :: 5 - Production/Stable
Classifier: Intended Audience :: Developers
Classifier: Topic :: Software Development :: Libraries :: Python Modules
Classifier: License :: OSI Approved :: MIT License
Classifier: Programming Language :: Python :: 2
Classifier: Programming Language :: Python :: 2.7
Classifier: Programming Language :: Python :: 3
Classifier: Programming Language :: Python :: 3.3
Classifier: Programming Language :: Python :: 3.4
Classifier: Programming Language :: Python :: 3.5
Classifier: Programming Language :: Python :: 3.6
Classifier: Programming Language :: Python :: 3.7
